ghinbox/__init__.py
ghinbox/auth.py
ghinbox/fixtures.py
ghinbox/github_api.py
ghinbox/run_flow.py
ghinbox/token.py
ghinbox/api/__init__.py
ghinbox/api/app.py
ghinbox/api/fetcher.py
ghinbox/api/github_proxy.py
ghinbox/api/models.py
ghinbox/api/routes.py
ghinbox/api/server.py
ghinbox/flows/__init__.py
ghinbox/flows/anchor_tracking.py
ghinbox/flows/base.py
ghinbox/flows/basic_notification.py
ghinbox/flows/comment_fetch_marks_read.py
ghinbox/flows/comment_prefetch_validation.py
ghinbox/flows/done_then_close.py
ghinbox/flows/notification_timestamps.py
ghinbox/flows/pagination.py
ghinbox/flows/parser_validation.py
ghinbox/flows/prod_notifications_snapshot.py
ghinbox/flows/prod_undo.py
ghinbox/flows/read_vs_done.py
ghinbox/parser/__init__.py
ghinbox/parser/notifications.py
ghinbox/webapp/index.html
ghinbox/webapp/notifications-actions.js
ghinbox/webapp/notifications-comments.js
ghinbox/webapp/notifications-core.js
ghinbox/webapp/notifications-idb.js
ghinbox/webapp/notifications-sync.js
ghinbox/webapp/notifications-ui.js
ghinbox/webapp/notifications.css
ghinbox/webapp/notifications.html
ghinbox/webapp/notifications.js
ghinbox-0.2.1.dist-info/METADATA
ghinbox-0.2.1.dist-info/WHEEL
ghinbox-0.2.1.dist-info/entry_points.txt
ghinbox-0.2.1.dist-info/RECORD
