Metadata-Version: 2.4
Name: ghinbox
Version: 0.2.1
Summary: GitHub notification simulation and testing tool for bulk notification management
License: MIT
Requires-Python: >=3.12
Requires-Dist: beautifulsoup4>=4.12.0
Requires-Dist: fastapi>=0.115.0
Requires-Dist: httpx>=0.28.0
Requires-Dist: lxml>=5.0.0
Requires-Dist: playwright>=1.49.0
Requires-Dist: uvicorn>=0.34.0
